disturbia/__init__.py
disturbia/distribute.py
disturbia/version.py
disturbia-0.0.1.dist-info/LICENSE
disturbia-0.0.1.dist-info/METADATA
disturbia-0.0.1.dist-info/WHEEL
disturbia-0.0.1.dist-info/top_level.txt
disturbia-0.0.1.dist-info/RECORD
