Metadata-Version: 2.1
Name: disturbia
Version: 0.0.1
Summary: Library for set of simple methods regarding distribution.
Home-page: https://github.com/ikhurramraza/disturbia
Author: Khurram Raza
Author-email: ikhurramraza@gmail.com
License: MIT
Keywords: distribution sampling
Platform: UNKNOWN
Classifier: License :: OSI Approved :: MIT License
Requires-Python: >=3.0, <4
